plotly_ex/__init__.py
plotly_ex/plotly_ex.py
plotly_ex-0.0.6.dist-info/LICENSE
plotly_ex-0.0.6.dist-info/METADATA
plotly_ex-0.0.6.dist-info/WHEEL
plotly_ex-0.0.6.dist-info/top_level.txt
plotly_ex-0.0.6.dist-info/RECORD
