Metadata-Version: 2.1
Name: plotly-ex
Version: 0.0.6
Summary: plotly extension
Author-email: "Fujihara S." <sierra.fujihara@gmail.com>
Classifier: Programming Language :: Python :: 3
Classifier: License :: OSI Approved :: MIT License
Classifier: Operating System :: OS Independent
Requires-Python: >=3.8
License-File: LICENSE
Requires-Dist: plotly <6,>=5.0
